lz_drip/__init__.py
lz_drip/bundle.py
lz_drip/file_utils.py
lz_drip/salt_arrival.py
lz_drip/spade_reception.py
lz_drip-0.0.8.dist-info/LICENSE.txt
lz_drip-0.0.8.dist-info/METADATA
lz_drip-0.0.8.dist-info/WHEEL
lz_drip-0.0.8.dist-info/entry_points.txt
lz_drip-0.0.8.dist-info/top_level.txt
lz_drip-0.0.8.dist-info/RECORD
